{
    "metadata": {
        "timestamp": "2026-01-24T21:47:09.444123",
        "vidore_benchmark_version": "5.0.0"
    },
    "metrics": {
        "vidore/vidore_v3_finance_fr": {
            "ndcg_at_1": 0.25391,
            "ndcg_at_3": 0.26912,
            "ndcg_at_5": 0.28532,
            "ndcg_at_10": 0.30978,
            "ndcg_at_20": 0.34306,
            "ndcg_at_50": 0.37997,
            "ndcg_at_100": 0.40068,
            "map_at_1": 0.11419,
            "map_at_3": 0.17534,
            "map_at_5": 0.19718,
            "map_at_10": 0.21894,
            "map_at_20": 0.23372,
            "map_at_50": 0.24518,
            "map_at_100": 0.24928,
            "recall_at_1": 0.11419,
            "recall_at_3": 0.22488,
            "recall_at_5": 0.28931,
            "recall_at_10": 0.37657,
            "recall_at_20": 0.47627,
            "recall_at_50": 0.60277,
            "recall_at_100": 0.68677,
            "precision_at_1": 0.27292,
            "precision_at_3": 0.20486,
            "precision_at_5": 0.16979,
            "precision_at_10": 0.1201,
            "precision_at_20": 0.08195,
            "precision_at_50": 0.04534,
            "precision_at_100": 0.02715,
            "mrr_at_1": 0.26979166666666665,
            "mrr_at_3": 0.3600694444444449,
            "mrr_at_5": 0.38137152777777866,
            "mrr_at_10": 0.3942323908730166,
            "mrr_at_20": 0.4010818783970881,
            "mrr_at_50": 0.4037687151184294,
            "mrr_at_100": 0.4044262612633102,
            "naucs_at_1_max": 0.16388853712336973,
            "naucs_at_1_std": 0.0298366695429634,
            "naucs_at_1_diff1": 0.2934595664350905,
            "naucs_at_3_max": 0.169500497028316,
            "naucs_at_3_std": 0.052658577198773496,
            "naucs_at_3_diff1": 0.14446453063330197,
            "naucs_at_5_max": 0.16388896297833516,
            "naucs_at_5_std": 0.07915853760877878,
            "naucs_at_5_diff1": 0.07985168955380013,
            "naucs_at_10_max": 0.1534652640478889,
            "naucs_at_10_std": 0.09124147186423366,
            "naucs_at_10_diff1": 0.01399825854884485,
            "naucs_at_20_max": 0.15235906934920065,
            "naucs_at_20_std": 0.12236272356505384,
            "naucs_at_20_diff1": -0.018275462132297735,
            "naucs_at_50_max": 0.13742840620440797,
            "naucs_at_50_std": 0.15247396449498504,
            "naucs_at_50_diff1": -0.04349806824078767,
            "naucs_at_100_max": 0.12137803827536175,
            "naucs_at_100_std": 0.15055492165941098,
            "naucs_at_100_diff1": -0.048065048446024494
        },
        "vidore/docvqa_test_subsampled": {
            "ndcg_at_1": 0.44124,
            "ndcg_at_3": 0.5294,
            "ndcg_at_5": 0.55287,
            "ndcg_at_10": 0.57291,
            "ndcg_at_20": 0.59216,
            "ndcg_at_50": 0.60826,
            "ndcg_at_100": 0.61564,
            "map_at_1": 0.44124,
            "map_at_3": 0.50776,
            "map_at_5": 0.52062,
            "map_at_10": 0.52886,
            "map_at_20": 0.53425,
            "map_at_50": 0.53694,
            "map_at_100": 0.53765,
            "recall_at_1": 0.44124,
            "recall_at_3": 0.59202,
            "recall_at_5": 0.64967,
            "recall_at_10": 0.71175,
            "recall_at_20": 0.78714,
            "recall_at_50": 0.86696,
            "recall_at_100": 0.91131,
            "precision_at_1": 0.44124,
            "precision_at_3": 0.19734,
            "precision_at_5": 0.12993,
            "precision_at_10": 0.07118,
            "precision_at_20": 0.03936,
            "precision_at_50": 0.01734,
            "precision_at_100": 0.00911,
            "mrr_at_1": 0.44124168514412415,
            "mrr_at_3": 0.5066518847006654,
            "mrr_at_5": 0.5201773835920178,
            "mrr_at_10": 0.5282546721571112,
            "mrr_at_20": 0.5338230212844934,
            "mrr_at_50": 0.5364629488108431,
            "mrr_at_100": 0.5372121333631136,
            "naucs_at_1_max": 0.1721605174093785,
            "naucs_at_1_std": -0.23600939324565823,
            "naucs_at_1_diff1": 0.7432164128269139,
            "naucs_at_3_max": 0.23108931752629228,
            "naucs_at_3_std": -0.1917549589188899,
            "naucs_at_3_diff1": 0.6517765776422841,
            "naucs_at_5_max": 0.2956569413456997,
            "naucs_at_5_std": -0.16204357580370687,
            "naucs_at_5_diff1": 0.6292208888944102,
            "naucs_at_10_max": 0.3477711907965929,
            "naucs_at_10_std": -0.1427365882876794,
            "naucs_at_10_diff1": 0.6264925073426717,
            "naucs_at_20_max": 0.38118917762957055,
            "naucs_at_20_std": -0.05871675953011763,
            "naucs_at_20_diff1": 0.6101159889375903,
            "naucs_at_50_max": 0.5711586236226472,
            "naucs_at_50_std": 0.20502869679370356,
            "naucs_at_50_diff1": 0.5912309470600257,
            "naucs_at_100_max": 0.6922112203805308,
            "naucs_at_100_std": 0.36317630171775195,
            "naucs_at_100_diff1": 0.6219611541326312
        },
        "vidore/biomedical_lectures_v2": {
            "ndcg_at_1": 0.45156,
            "ndcg_at_3": 0.47745,
            "ndcg_at_5": 0.50534,
            "ndcg_at_10": 0.54728,
            "ndcg_at_20": 0.5772,
            "ndcg_at_50": 0.60739,
            "ndcg_at_100": 0.6217,
            "map_at_1": 0.26708,
            "map_at_3": 0.38087,
            "map_at_5": 0.41939,
            "map_at_10": 0.4517,
            "map_at_20": 0.46721,
            "map_at_50": 0.47684,
            "map_at_100": 0.48003,
            "recall_at_1": 0.26708,
            "recall_at_3": 0.45881,
            "recall_at_5": 0.55334,
            "recall_at_10": 0.67575,
            "recall_at_20": 0.7645,
            "recall_at_50": 0.86387,
            "recall_at_100": 0.91501,
            "precision_at_1": 0.45156,
            "precision_at_3": 0.30573,
            "precision_at_5": 0.24,
            "precision_at_10": 0.15828,
            "precision_at_20": 0.09547,
            "precision_at_50": 0.04716,
            "precision_at_100": 0.02675,
            "mrr_at_1": 0.446875,
            "mrr_at_3": 0.5473958333333331,
            "mrr_at_5": 0.5678645833333329,
            "mrr_at_10": 0.5808023313492063,
            "mrr_at_20": 0.5842168683556186,
            "mrr_at_50": 0.586134906667982,
            "mrr_at_100": 0.5862756707107086,
            "naucs_at_1_max": 0.14111322427237552,
            "naucs_at_1_std": -0.13119660656781412,
            "naucs_at_1_diff1": 0.4196240119720027,
            "naucs_at_3_max": 0.09144842890705027,
            "naucs_at_3_std": -0.0977567666283751,
            "naucs_at_3_diff1": 0.07327465523061967,
            "naucs_at_5_max": 0.05574776333216232,
            "naucs_at_5_std": -0.11628330224973203,
            "naucs_at_5_diff1": -0.04074384409546706,
            "naucs_at_10_max": 0.06878649193255144,
            "naucs_at_10_std": -0.060442312181490626,
            "naucs_at_10_diff1": -0.12114646231299823,
            "naucs_at_20_max": 0.07315377523723823,
            "naucs_at_20_std": -0.0034441703512517155,
            "naucs_at_20_diff1": -0.17274756128893573,
            "naucs_at_50_max": 0.025957592624361973,
            "naucs_at_50_std": 0.011181657956659189,
            "naucs_at_50_diff1": -0.23764346723096308,
            "naucs_at_100_max": -0.007598289380218229,
            "naucs_at_100_std": 0.012421454264958562,
            "naucs_at_100_diff1": -0.25349709222172573
        },
        "vidore/syntheticDocQA_healthcare_industry_test": {
            "ndcg_at_1": 0.87,
            "ndcg_at_3": 0.92417,
            "ndcg_at_5": 0.94052,
            "ndcg_at_10": 0.94052,
            "ndcg_at_20": 0.94052,
            "ndcg_at_50": 0.94052,
            "ndcg_at_100": 0.94052,
            "map_at_1": 0.87,
            "map_at_3": 0.91167,
            "map_at_5": 0.92067,
            "map_at_10": 0.92067,
            "map_at_20": 0.92067,
            "map_at_50": 0.92067,
            "map_at_100": 0.92067,
            "recall_at_1": 0.87,
            "recall_at_3": 0.96,
            "recall_at_5": 1.0,
            "recall_at_10": 1.0,
            "recall_at_20": 1.0,
            "recall_at_50": 1.0,
            "recall_at_100": 1.0,
            "precision_at_1": 0.87,
            "precision_at_3": 0.32,
            "precision_at_5": 0.2,
            "precision_at_10": 0.1,
            "precision_at_20": 0.05,
            "precision_at_50": 0.02,
            "precision_at_100": 0.01,
            "mrr_at_1": 0.87,
            "mrr_at_3": 0.9116666666666666,
            "mrr_at_5": 0.9206666666666666,
            "mrr_at_10": 0.9206666666666666,
            "mrr_at_20": 0.9206666666666666,
            "mrr_at_50": 0.9206666666666666,
            "mrr_at_100": 0.9206666666666666,
            "naucs_at_1_max": 0.33511071613715465,
            "naucs_at_1_std": -0.7363178552914177,
            "naucs_at_1_diff1": 0.9309412723098575,
            "naucs_at_3_max": 0.8978758169934614,
            "naucs_at_3_std": -0.9213352007469611,
            "naucs_at_3_diff1": 1.0,
            "naucs_at_5_max": 1.0,
            "naucs_at_5_std": 1.0,
            "naucs_at_5_diff1": 1.0,
            "naucs_at_10_max": 1.0,
            "naucs_at_10_std": 1.0,
            "naucs_at_10_diff1": 1.0,
            "naucs_at_20_max": 1.0,
            "naucs_at_20_std": 1.0,
            "naucs_at_20_diff1": 1.0,
            "naucs_at_50_max": null,
            "naucs_at_50_std": null,
            "naucs_at_50_diff1": null,
            "naucs_at_100_max": null,
            "naucs_at_100_std": null,
            "naucs_at_100_diff1": null
        },
        "vidore/biomedical_lectures_eng_v2": {
            "ndcg_at_1": 0.5125,
            "ndcg_at_3": 0.52792,
            "ndcg_at_5": 0.55394,
            "ndcg_at_10": 0.5862,
            "ndcg_at_20": 0.61872,
            "ndcg_at_50": 0.64662,
            "ndcg_at_100": 0.65967,
            "map_at_1": 0.29517,
            "map_at_3": 0.42194,
            "map_at_5": 0.46271,
            "map_at_10": 0.49203,
            "map_at_20": 0.51019,
            "map_at_50": 0.51893,
            "map_at_100": 0.52201,
            "recall_at_1": 0.29517,
            "recall_at_3": 0.50205,
            "recall_at_5": 0.6028,
            "recall_at_10": 0.69933,
            "recall_at_20": 0.79286,
            "recall_at_50": 0.88559,
            "recall_at_100": 0.93098,
            "precision_at_1": 0.5125,
            "precision_at_3": 0.33958,
            "precision_at_5": 0.26,
            "precision_at_10": 0.16688,
            "precision_at_20": 0.10156,
            "precision_at_50": 0.049,
            "precision_at_100": 0.02756,
            "mrr_at_1": 0.5125,
            "mrr_at_3": 0.6083333333333332,
            "mrr_at_5": 0.6270833333333331,
            "mrr_at_10": 0.6347891865079365,
            "mrr_at_20": 0.637751079598506,
            "mrr_at_50": 0.6398384882493271,
            "mrr_at_100": 0.6398384882493271,
            "naucs_at_1_max": 0.17639566075616223,
            "naucs_at_1_std": -0.25919896074097803,
            "naucs_at_1_diff1": 0.5020498371940008,
            "naucs_at_3_max": 0.03590699412374355,
            "naucs_at_3_std": -0.20043771657851514,
            "naucs_at_3_diff1": 0.03343371752156324,
            "naucs_at_5_max": 0.03609702728203938,
            "naucs_at_5_std": -0.13447170649504178,
            "naucs_at_5_diff1": -0.08104942781512378,
            "naucs_at_10_max": 0.0350935031587635,
            "naucs_at_10_std": -0.06194768540482326,
            "naucs_at_10_diff1": -0.1410199711060902,
            "naucs_at_20_max": 0.01607505349207223,
            "naucs_at_20_std": -0.01278534380525908,
            "naucs_at_20_diff1": -0.222113432735038,
            "naucs_at_50_max": 0.01227987418706088,
            "naucs_at_50_std": 0.09579357686458792,
            "naucs_at_50_diff1": -0.28572888231176996,
            "naucs_at_100_max": -0.0010195277673923507,
            "naucs_at_100_std": 0.13732852089384842,
            "naucs_at_100_diff1": -0.2751143194041012
        },
        "vidore/syntheticDocQA_energy_test": {
            "ndcg_at_1": 0.86,
            "ndcg_at_3": 0.90286,
            "ndcg_at_5": 0.90716,
            "ndcg_at_10": 0.9173,
            "ndcg_at_20": 0.92009,
            "ndcg_at_50": 0.92425,
            "ndcg_at_100": 0.92425,
            "map_at_1": 0.86,
            "map_at_3": 0.89333,
            "map_at_5": 0.89583,
            "map_at_10": 0.90028,
            "map_at_20": 0.90119,
            "map_at_50": 0.90194,
            "map_at_100": 0.90194,
            "recall_at_1": 0.86,
            "recall_at_3": 0.93,
            "recall_at_5": 0.94,
            "recall_at_10": 0.97,
            "recall_at_20": 0.98,
            "recall_at_50": 1.0,
            "recall_at_100": 1.0,
            "precision_at_1": 0.86,
            "precision_at_3": 0.31,
            "precision_at_5": 0.188,
            "precision_at_10": 0.097,
            "precision_at_20": 0.049,
            "precision_at_50": 0.02,
            "precision_at_100": 0.01,
            "mrr_at_1": 0.86,
            "mrr_at_3": 0.8933333333333333,
            "mrr_at_5": 0.8978333333333333,
            "mrr_at_10": 0.9019285714285715,
            "mrr_at_20": 0.9024285714285715,
            "mrr_at_50": 0.9027063492063493,
            "mrr_at_100": 0.9027063492063493,
            "naucs_at_1_max": 0.39898849937647185,
            "naucs_at_1_std": -0.5042607731744477,
            "naucs_at_1_diff1": 0.8986767354856583,
            "naucs_at_3_max": 0.23356009070294853,
            "naucs_at_3_std": -0.9220354808590062,
            "naucs_at_3_diff1": 0.9229691876750693,
            "naucs_at_5_max": 0.12760659819483386,
            "naucs_at_5_std": -1.0961718020541558,
            "naucs_at_5_diff1": 0.9319172113289762,
            "naucs_at_10_max": 0.4936196700902597,
            "naucs_at_10_std": -1.1517273576097071,
            "naucs_at_10_diff1": 0.8638344226579531,
            "naucs_at_20_max": 0.5613912231559286,
            "naucs_at_20_std": -0.8576097105508901,
            "naucs_at_20_diff1": 0.7957516339869297,
            "naucs_at_50_max": null,
            "naucs_at_50_std": null,
            "naucs_at_50_diff1": null,
            "naucs_at_100_max": null,
            "naucs_at_100_std": null,
            "naucs_at_100_diff1": null
        },
        "vidore/syntheticDocQA_government_reports_test": {
            "ndcg_at_1": 0.88,
            "ndcg_at_3": 0.92655,
            "ndcg_at_5": 0.93516,
            "ndcg_at_10": 0.93872,
            "ndcg_at_20": 0.93872,
            "ndcg_at_50": 0.94088,
            "ndcg_at_100": 0.94088,
            "map_at_1": 0.88,
            "map_at_3": 0.915,
            "map_at_5": 0.92,
            "map_at_10": 0.92167,
            "map_at_20": 0.92167,
            "map_at_50": 0.92208,
            "map_at_100": 0.92208,
            "recall_at_1": 0.88,
            "recall_at_3": 0.96,
            "recall_at_5": 0.98,
            "recall_at_10": 0.99,
            "recall_at_20": 0.99,
            "recall_at_50": 1.0,
            "recall_at_100": 1.0,
            "precision_at_1": 0.88,
            "precision_at_3": 0.32,
            "precision_at_5": 0.196,
            "precision_at_10": 0.099,
            "precision_at_20": 0.0495,
            "precision_at_50": 0.02,
            "precision_at_100": 0.01,
            "mrr_at_1": 0.89,
            "mrr_at_3": 0.92,
            "mrr_at_5": 0.925,
            "mrr_at_10": 0.9266666666666665,
            "mrr_at_20": 0.9266666666666665,
            "mrr_at_50": 0.9270833333333333,
            "mrr_at_100": 0.9270833333333333,
            "naucs_at_1_max": 0.2697661469933189,
            "naucs_at_1_std": -0.1632198536430158,
            "naucs_at_1_diff1": 0.9035555202036274,
            "naucs_at_3_max": 0.24556489262371492,
            "naucs_at_3_std": -0.3085901027077491,
            "naucs_at_3_diff1": 0.9019607843137251,
            "naucs_at_5_max": 1.0,
            "naucs_at_5_std": -0.8085901027077421,
            "naucs_at_5_diff1": 0.9346405228758136,
            "naucs_at_10_max": 1.0,
            "naucs_at_10_std": -1.7399626517273863,
            "naucs_at_10_diff1": 1.0,
            "naucs_at_20_max": 1.0,
            "naucs_at_20_std": -1.7399626517273863,
            "naucs_at_20_diff1": 1.0,
            "naucs_at_50_max": null,
            "naucs_at_50_std": null,
            "naucs_at_50_diff1": null,
            "naucs_at_100_max": null,
            "naucs_at_100_std": null,
            "naucs_at_100_diff1": null
        },
        "vidore/vidore_v3_hr": {
            "ndcg_at_1": 0.41614,
            "ndcg_at_3": 0.4178,
            "ndcg_at_5": 0.4292,
            "ndcg_at_10": 0.45717,
            "ndcg_at_20": 0.4909,
            "ndcg_at_50": 0.5373,
            "ndcg_at_100": 0.56222,
            "map_at_1": 0.1616,
            "map_at_3": 0.25585,
            "map_at_5": 0.2932,
            "map_at_10": 0.33345,
            "map_at_20": 0.36007,
            "map_at_50": 0.38039,
            "map_at_100": 0.38694,
            "recall_at_1": 0.1616,
            "recall_at_3": 0.3147,
            "recall_at_5": 0.39854,
            "recall_at_10": 0.51239,
            "recall_at_20": 0.63224,
            "recall_at_50": 0.77413,
            "recall_at_100": 0.86367,
            "precision_at_1": 0.44549,
            "precision_at_3": 0.32075,
            "precision_at_5": 0.26572,
            "precision_at_10": 0.19423,
            "precision_at_20": 0.13208,
            "precision_at_50": 0.07265,
            "precision_at_100": 0.04295,
            "mrr_at_1": 0.4334381551362683,
            "mrr_at_3": 0.5288259958071287,
            "mrr_at_5": 0.547274633123691,
            "mrr_at_10": 0.55848016704935,
            "mrr_at_20": 0.5637690463349581,
            "mrr_at_50": 0.5656110699816015,
            "mrr_at_100": 0.5660394416790424,
            "naucs_at_1_max": 0.14137006306668928,
            "naucs_at_1_std": -0.08642763527390147,
            "naucs_at_1_diff1": 0.330742182899046,
            "naucs_at_3_max": 0.1496522045801126,
            "naucs_at_3_std": -0.049751756117920064,
            "naucs_at_3_diff1": 0.21135323237294956,
            "naucs_at_5_max": 0.13744033651742033,
            "naucs_at_5_std": -0.054739532700169215,
            "naucs_at_5_diff1": 0.16933752073304095,
            "naucs_at_10_max": 0.12125776558566718,
            "naucs_at_10_std": -0.07179747883260275,
            "naucs_at_10_diff1": 0.10781250416664466,
            "naucs_at_20_max": 0.1093453797392644,
            "naucs_at_20_std": -0.07936483890784635,
            "naucs_at_20_diff1": 0.07361659449216432,
            "naucs_at_50_max": 0.08070354241647174,
            "naucs_at_50_std": -0.05868498159032949,
            "naucs_at_50_diff1": 0.02197675446692394,
            "naucs_at_100_max": 0.05693584060496446,
            "naucs_at_100_std": -0.05353730115645356,
            "naucs_at_100_diff1": 0.022281061435168642
        },
        "vidore/tatdqa_test": {
            "ndcg_at_1": 0.4678,
            "ndcg_at_3": 0.58379,
            "ndcg_at_5": 0.61984,
            "ndcg_at_10": 0.65279,
            "ndcg_at_20": 0.66848,
            "ndcg_at_50": 0.67943,
            "ndcg_at_100": 0.68242,
            "map_at_1": 0.4678,
            "map_at_3": 0.55559,
            "map_at_5": 0.57576,
            "map_at_10": 0.58966,
            "map_at_20": 0.59405,
            "map_at_50": 0.59595,
            "map_at_100": 0.59623,
            "recall_at_1": 0.4678,
            "recall_at_3": 0.66525,
            "recall_at_5": 0.75213,
            "recall_at_10": 0.85237,
            "recall_at_20": 0.91373,
            "recall_at_50": 0.96719,
            "recall_at_100": 0.98542,
            "precision_at_1": 0.4678,
            "precision_at_3": 0.22175,
            "precision_at_5": 0.15043,
            "precision_at_10": 0.08524,
            "precision_at_20": 0.04569,
            "precision_at_50": 0.01934,
            "precision_at_100": 0.00985,
            "mrr_at_1": 0.4671931956257594,
            "mrr_at_3": 0.5559943296881336,
            "mrr_at_5": 0.576073309031998,
            "mrr_at_10": 0.5898843275665877,
            "mrr_at_20": 0.5942676076590645,
            "mrr_at_50": 0.5961922481453747,
            "mrr_at_100": 0.596464662062626,
            "naucs_at_1_max": 0.03911759015721688,
            "naucs_at_1_std": -0.2713768297467013,
            "naucs_at_1_diff1": 0.6312226983838214,
            "naucs_at_3_max": 0.053724489845446304,
            "naucs_at_3_std": -0.28958292298946964,
            "naucs_at_3_diff1": 0.5158304731395056,
            "naucs_at_5_max": 0.0990109582696,
            "naucs_at_5_std": -0.2598075028206234,
            "naucs_at_5_diff1": 0.4835869200711715,
            "naucs_at_10_max": 0.2611613953929769,
            "naucs_at_10_std": -0.1027080989127862,
            "naucs_at_10_diff1": 0.39795437945645507,
            "naucs_at_20_max": 0.500648388620534,
            "naucs_at_20_std": 0.12242835961650934,
            "naucs_at_20_diff1": 0.3853192223537299,
            "naucs_at_50_max": 0.6517626415542069,
            "naucs_at_50_std": 0.32998053861480575,
            "naucs_at_50_diff1": 0.5398539756360039,
            "naucs_at_100_max": 0.8150214503378631,
            "naucs_at_100_std": 0.7442650125149798,
            "naucs_at_100_diff1": 0.5356549693610877
        },
        "vidore/vidore_v3_industrial": {
            "ndcg_at_1": 0.2871,
            "ndcg_at_3": 0.31237,
            "ndcg_at_5": 0.32673,
            "ndcg_at_10": 0.34865,
            "ndcg_at_20": 0.37827,
            "ndcg_at_50": 0.41473,
            "ndcg_at_100": 0.43926,
            "map_at_1": 0.15015,
            "map_at_3": 0.21817,
            "map_at_5": 0.23947,
            "map_at_10": 0.26208,
            "map_at_20": 0.27742,
            "map_at_50": 0.28856,
            "map_at_100": 0.29368,
            "recall_at_1": 0.15015,
            "recall_at_3": 0.26662,
            "recall_at_5": 0.32128,
            "recall_at_10": 0.40753,
            "recall_at_20": 0.50094,
            "recall_at_50": 0.62108,
            "recall_at_100": 0.70604,
            "precision_at_1": 0.30978,
            "precision_at_3": 0.21849,
            "precision_at_5": 0.17656,
            "precision_at_10": 0.1258,
            "precision_at_20": 0.08566,
            "precision_at_50": 0.0484,
            "precision_at_100": 0.03097,
            "mrr_at_1": 0.3127208480565371,
            "mrr_at_3": 0.3900667451904203,
            "mrr_at_5": 0.4080585001963101,
            "mrr_at_10": 0.4233334735543222,
            "mrr_at_20": 0.4295692298591363,
            "mrr_at_50": 0.43244022053538944,
            "mrr_at_100": 0.43306954958160243,
            "naucs_at_1_max": 0.1898968945685428,
            "naucs_at_1_std": 0.0010166278766818074,
            "naucs_at_1_diff1": 0.4161266724961226,
            "naucs_at_3_max": 0.14966661577974968,
            "naucs_at_3_std": -0.017849443134799962,
            "naucs_at_3_diff1": 0.20612116460041724,
            "naucs_at_5_max": 0.14818945217864485,
            "naucs_at_5_std": -0.0070385705030281956,
            "naucs_at_5_diff1": 0.14759977620471693,
            "naucs_at_10_max": 0.13467279271773477,
            "naucs_at_10_std": 0.0036821534784780897,
            "naucs_at_10_diff1": 0.05348862087485507,
            "naucs_at_20_max": 0.12897848871077253,
            "naucs_at_20_std": 0.02589912388996348,
            "naucs_at_20_diff1": 0.0013253857823829927,
            "naucs_at_50_max": 0.09329595000661453,
            "naucs_at_50_std": 0.04007095296802601,
            "naucs_at_50_diff1": -0.03847629728577126,
            "naucs_at_100_max": 0.05878840683045367,
            "naucs_at_100_std": 0.043883706706626814,
            "naucs_at_100_diff1": -0.049343924402141394
        },
        "vidore/vidore_v3_computer_science": {
            "ndcg_at_1": 0.63953,
            "ndcg_at_3": 0.63371,
            "ndcg_at_5": 0.64277,
            "ndcg_at_10": 0.67621,
            "ndcg_at_20": 0.71491,
            "ndcg_at_50": 0.74663,
            "ndcg_at_100": 0.75594,
            "map_at_1": 0.25461,
            "map_at_3": 0.42323,
            "map_at_5": 0.4909,
            "map_at_10": 0.55766,
            "map_at_20": 0.59301,
            "map_at_50": 0.61071,
            "map_at_100": 0.61368,
            "recall_at_1": 0.25461,
            "recall_at_3": 0.46886,
            "recall_at_5": 0.58039,
            "recall_at_10": 0.72832,
            "recall_at_20": 0.8363,
            "recall_at_50": 0.92602,
            "recall_at_100": 0.95874,
            "precision_at_1": 0.7093,
            "precision_at_3": 0.51938,
            "precision_at_5": 0.4245,
            "precision_at_10": 0.29791,
            "precision_at_20": 0.18477,
            "precision_at_50": 0.08695,
            "precision_at_100": 0.04586,
            "mrr_at_1": 0.7108527131782946,
            "mrr_at_3": 0.7816537467700264,
            "mrr_at_5": 0.7949095607235152,
            "mrr_at_10": 0.8006853697551378,
            "mrr_at_20": 0.8019509265837301,
            "mrr_at_50": 0.8021667065162925,
            "mrr_at_100": 0.8021883364556126,
            "naucs_at_1_max": 0.20536332551988126,
            "naucs_at_1_std": -0.05922309914482103,
            "naucs_at_1_diff1": 0.4221500612890049,
            "naucs_at_3_max": 0.22659824397712858,
            "naucs_at_3_std": 0.009076772171582845,
            "naucs_at_3_diff1": 0.051058637766453585,
            "naucs_at_5_max": 0.2370157270317512,
            "naucs_at_5_std": 0.08278820639916855,
            "naucs_at_5_diff1": -0.06687292208202583,
            "naucs_at_10_max": 0.21080865742754223,
            "naucs_at_10_std": 0.1220573547155036,
            "naucs_at_10_diff1": -0.1548867254071365,
            "naucs_at_20_max": 0.16321006972339383,
            "naucs_at_20_std": 0.11143281819753309,
            "naucs_at_20_diff1": -0.17449574093190387,
            "naucs_at_50_max": 0.11121364061734496,
            "naucs_at_50_std": 0.07021813590482423,
            "naucs_at_50_diff1": -0.16928139564348033,
            "naucs_at_100_max": 0.08109223917742991,
            "naucs_at_100_std": 0.06103036634906517,
            "naucs_at_100_diff1": -0.16412744923861594
        },
        "vidore/vidore_v3_pharmaceuticals": {
            "ndcg_at_1": 0.44368,
            "ndcg_at_3": 0.47115,
            "ndcg_at_5": 0.48254,
            "ndcg_at_10": 0.50622,
            "ndcg_at_20": 0.5444,
            "ndcg_at_50": 0.5839,
            "ndcg_at_100": 0.60327,
            "map_at_1": 0.22073,
            "map_at_3": 0.32187,
            "map_at_5": 0.35379,
            "map_at_10": 0.38973,
            "map_at_20": 0.41812,
            "map_at_50": 0.4351,
            "map_at_100": 0.44004,
            "recall_at_1": 0.22073,
            "recall_at_3": 0.38828,
            "recall_at_5": 0.467,
            "recall_at_10": 0.57866,
            "recall_at_20": 0.6955,
            "recall_at_50": 0.81291,
            "recall_at_100": 0.88214,
            "precision_at_1": 0.46658,
            "precision_at_3": 0.33425,
            "precision_at_5": 0.26667,
            "precision_at_10": 0.1897,
            "precision_at_20": 0.12944,
            "precision_at_50": 0.06745,
            "precision_at_100": 0.03847,
            "mrr_at_1": 0.4661172161172161,
            "mrr_at_3": 0.5760836385836391,
            "mrr_at_5": 0.5947420634920646,
            "mrr_at_10": 0.6058449982557129,
            "mrr_at_20": 0.6095303450669737,
            "mrr_at_50": 0.6106634135128967,
            "mrr_at_100": 0.6109656987902506,
            "naucs_at_1_max": 0.08017122644612944,
            "naucs_at_1_std": -0.18680196387581013,
            "naucs_at_1_diff1": 0.4028623270702055,
            "naucs_at_3_max": 0.13980108768732974,
            "naucs_at_3_std": -0.13232866427442935,
            "naucs_at_3_diff1": 0.11333272346542436,
            "naucs_at_5_max": 0.13971771312622183,
            "naucs_at_5_std": -0.1028041519293198,
            "naucs_at_5_diff1": -0.0025389819468506114,
            "naucs_at_10_max": 0.14679364568399286,
            "naucs_at_10_std": -0.0605249766776666,
            "naucs_at_10_diff1": -0.06662812483942238,
            "naucs_at_20_max": 0.17690143305165756,
            "naucs_at_20_std": -0.014115999676295343,
            "naucs_at_20_diff1": -0.08026424047121804,
            "naucs_at_50_max": 0.17291997997908848,
            "naucs_at_50_std": 0.04824633939133898,
            "naucs_at_50_diff1": -0.11536044913956266,
            "naucs_at_100_max": 0.1686839435965372,
            "naucs_at_100_std": 0.10313177425626492,
            "naucs_at_100_diff1": -0.14510363800299225
        },
        "vidore/infovqa_test_subsampled": {
            "ndcg_at_1": 0.78543,
            "ndcg_at_3": 0.83866,
            "ndcg_at_5": 0.85695,
            "ndcg_at_10": 0.86204,
            "ndcg_at_20": 0.86564,
            "ndcg_at_50": 0.86965,
            "ndcg_at_100": 0.87095,
            "map_at_1": 0.78543,
            "map_at_3": 0.82557,
            "map_at_5": 0.8357,
            "map_at_10": 0.83771,
            "map_at_20": 0.83871,
            "map_at_50": 0.83935,
            "map_at_100": 0.83946,
            "recall_at_1": 0.78543,
            "recall_at_3": 0.87652,
            "recall_at_5": 0.92105,
            "recall_at_10": 0.93725,
            "recall_at_20": 0.95142,
            "recall_at_50": 0.97166,
            "recall_at_100": 0.97976,
            "precision_at_1": 0.78543,
            "precision_at_3": 0.29217,
            "precision_at_5": 0.18421,
            "precision_at_10": 0.09372,
            "precision_at_20": 0.04757,
            "precision_at_50": 0.01943,
            "precision_at_100": 0.0098,
            "mrr_at_1": 0.7854251012145749,
            "mrr_at_3": 0.8255735492577596,
            "mrr_at_5": 0.8357962213225367,
            "mrr_at_10": 0.8383514876935926,
            "mrr_at_20": 0.8391889178073385,
            "mrr_at_50": 0.8397916150730982,
            "mrr_at_100": 0.8399431597974818,
            "naucs_at_1_max": 0.44226273184850523,
            "naucs_at_1_std": -0.22808621674528007,
            "naucs_at_1_diff1": 0.8563740394999086,
            "naucs_at_3_max": 0.502392879176532,
            "naucs_at_3_std": -0.1112254928669056,
            "naucs_at_3_diff1": 0.8108527068655283,
            "naucs_at_5_max": 0.7085439399173851,
            "naucs_at_5_std": 0.16426595598688995,
            "naucs_at_5_diff1": 0.7836934321509329,
            "naucs_at_10_max": 0.7744311186408459,
            "naucs_at_10_std": 0.2965176785250613,
            "naucs_at_10_diff1": 0.7679220728704245,
            "naucs_at_20_max": 0.8566023115675981,
            "naucs_at_20_std": 0.5271157886989453,
            "naucs_at_20_diff1": 0.7342606934428615,
            "naucs_at_50_max": 0.8373506794335622,
            "naucs_at_50_std": 0.5760526406052691,
            "naucs_at_50_diff1": 0.6704430617131771,
            "naucs_at_100_max": 0.8730853301970164,
            "naucs_at_100_std": 0.6770805994258896,
            "naucs_at_100_diff1": 0.6370845325834673
        },
        "vidore/vidore_v3_finance_en": {
            "ndcg_at_1": 0.39024,
            "ndcg_at_3": 0.38261,
            "ndcg_at_5": 0.39454,
            "ndcg_at_10": 0.42647,
            "ndcg_at_20": 0.45973,
            "ndcg_at_50": 0.49546,
            "ndcg_at_100": 0.51688,
            "map_at_1": 0.18209,
            "map_at_3": 0.25715,
            "map_at_5": 0.2883,
            "map_at_10": 0.3192,
            "map_at_20": 0.33782,
            "map_at_50": 0.3495,
            "map_at_100": 0.35392,
            "recall_at_1": 0.18209,
            "recall_at_3": 0.30643,
            "recall_at_5": 0.38195,
            "recall_at_10": 0.49287,
            "recall_at_20": 0.59532,
            "recall_at_50": 0.71409,
            "recall_at_100": 0.79465,
            "precision_at_1": 0.42125,
            "precision_at_3": 0.27742,
            "precision_at_5": 0.22287,
            "precision_at_10": 0.15782,
            "precision_at_20": 0.10227,
            "precision_at_50": 0.05315,
            "precision_at_100": 0.03155,
            "mrr_at_1": 0.41963322545846815,
            "mrr_at_3": 0.507281553398059,
            "mrr_at_5": 0.5260248112189874,
            "mrr_at_10": 0.5401061197582238,
            "mrr_at_20": 0.5451956464195096,
            "mrr_at_50": 0.5470609723716479,
            "mrr_at_100": 0.5475062308591808,
            "naucs_at_1_max": 0.20703096362918721,
            "naucs_at_1_std": -0.009675019664872341,
            "naucs_at_1_diff1": 0.40626360594557254,
            "naucs_at_3_max": 0.20124494127221926,
            "naucs_at_3_std": -0.0003511265746083746,
            "naucs_at_3_diff1": 0.1715423400769236,
            "naucs_at_5_max": 0.19475613067917832,
            "naucs_at_5_std": 0.012815592736442569,
            "naucs_at_5_diff1": 0.1086932007089066,
            "naucs_at_10_max": 0.18818248783454644,
            "naucs_at_10_std": 0.046634363309921024,
            "naucs_at_10_diff1": 0.07148571247912423,
            "naucs_at_20_max": 0.1562456078072769,
            "naucs_at_20_std": 0.06474989303184482,
            "naucs_at_20_diff1": 0.04514503706006612,
            "naucs_at_50_max": 0.13270113726683572,
            "naucs_at_50_std": 0.09178380182195921,
            "naucs_at_50_diff1": 0.02215232234912462,
            "naucs_at_100_max": 0.0938860380658014,
            "naucs_at_100_std": 0.10710058525452396,
            "naucs_at_100_diff1": 0.0014603709552864117
        },
        "vidore/vidore_v3_physics": {
            "ndcg_at_1": 0.36065,
            "ndcg_at_3": 0.37386,
            "ndcg_at_5": 0.38973,
            "ndcg_at_10": 0.4208,
            "ndcg_at_20": 0.46726,
            "ndcg_at_50": 0.52589,
            "ndcg_at_100": 0.5529,
            "map_at_1": 0.14151,
            "map_at_3": 0.20914,
            "map_at_5": 0.24232,
            "map_at_10": 0.28588,
            "map_at_20": 0.32432,
            "map_at_50": 0.35267,
            "map_at_100": 0.36103,
            "recall_at_1": 0.14151,
            "recall_at_3": 0.25769,
            "recall_at_5": 0.33482,
            "recall_at_10": 0.45976,
            "recall_at_20": 0.59943,
            "recall_at_50": 0.75851,
            "recall_at_100": 0.84601,
            "precision_at_1": 0.39735,
            "precision_at_3": 0.305,
            "precision_at_5": 0.26921,
            "precision_at_10": 0.2165,
            "precision_at_20": 0.16313,
            "precision_at_50": 0.09499,
            "precision_at_100": 0.05623,
            "mrr_at_1": 0.3868653421633554,
            "mrr_at_3": 0.5094738778513623,
            "mrr_at_5": 0.5311626195732176,
            "mrr_at_10": 0.5450674953572323,
            "mrr_at_20": 0.5493643576014993,
            "mrr_at_50": 0.5511116135145802,
            "mrr_at_100": 0.5514082662483467,
            "naucs_at_1_max": 0.033112599770141894,
            "naucs_at_1_std": -0.1412161844456813,
            "naucs_at_1_diff1": 0.26262469148530115,
            "naucs_at_3_max": 0.02551755783743411,
            "naucs_at_3_std": -0.15371178303813568,
            "naucs_at_3_diff1": 0.09287156147553238,
            "naucs_at_5_max": 0.03638314137442595,
            "naucs_at_5_std": -0.10909785325152488,
            "naucs_at_5_diff1": 0.009780968400642282,
            "naucs_at_10_max": 0.05259797535201004,
            "naucs_at_10_std": -0.04801581497332658,
            "naucs_at_10_diff1": -0.024414794591498118,
            "naucs_at_20_max": 0.0543973720641905,
            "naucs_at_20_std": 0.005917614282721645,
            "naucs_at_20_diff1": -0.05075719873513505,
            "naucs_at_50_max": 0.02489328140517539,
            "naucs_at_50_std": 0.05489989379475434,
            "naucs_at_50_diff1": -0.038667576333225144,
            "naucs_at_100_max": 0.0013962642398885289,
            "naucs_at_100_std": 0.08381429868344936,
            "naucs_at_100_diff1": -0.04371394851151226
        },
        "vidore/esg_reports_human_labeled_v2": {
            "ndcg_at_1": 0.48718,
            "ndcg_at_3": 0.4858,
            "ndcg_at_5": 0.53714,
            "ndcg_at_10": 0.5617,
            "ndcg_at_20": 0.58534,
            "ndcg_at_50": 0.60868,
            "ndcg_at_100": 0.6206,
            "map_at_1": 0.30065,
            "map_at_3": 0.40273,
            "map_at_5": 0.45284,
            "map_at_10": 0.47406,
            "map_at_20": 0.48429,
            "map_at_50": 0.4917,
            "map_at_100": 0.49353,
            "recall_at_1": 0.30065,
            "recall_at_3": 0.46603,
            "recall_at_5": 0.61603,
            "recall_at_10": 0.69328,
            "recall_at_20": 0.77373,
            "recall_at_50": 0.85456,
            "recall_at_100": 0.9124,
            "precision_at_1": 0.5,
            "precision_at_3": 0.28846,
            "precision_at_5": 0.23462,
            "precision_at_10": 0.13846,
            "precision_at_20": 0.07981,
            "precision_at_50": 0.03808,
            "precision_at_100": 0.02058,
            "mrr_at_1": 0.5384615384615384,
            "mrr_at_3": 0.592948717948718,
            "mrr_at_5": 0.6189102564102564,
            "mrr_at_10": 0.6299908424908426,
            "mrr_at_20": 0.6317390942390942,
            "mrr_at_50": 0.6350076780103955,
            "mrr_at_100": 0.6356074948602123,
            "naucs_at_1_max": 0.2847474051849878,
            "naucs_at_1_std": 0.17049489682225707,
            "naucs_at_1_diff1": 0.4058375340410245,
            "naucs_at_3_max": 0.18859113706949424,
            "naucs_at_3_std": 0.1151090005035426,
            "naucs_at_3_diff1": -0.0001639109022975381,
            "naucs_at_5_max": 0.34169219889418484,
            "naucs_at_5_std": 0.23069771962322486,
            "naucs_at_5_diff1": -0.11095328946143555,
            "naucs_at_10_max": 0.426751420910681,
            "naucs_at_10_std": 0.23443622371834597,
            "naucs_at_10_diff1": -0.17780239580247528,
            "naucs_at_20_max": 0.3697182838468573,
            "naucs_at_20_std": 0.16532155180391622,
            "naucs_at_20_diff1": -0.19110410095832306,
            "naucs_at_50_max": 0.3458085114109553,
            "naucs_at_50_std": 0.21818668804329758,
            "naucs_at_50_diff1": -0.20935192709624734,
            "naucs_at_100_max": 0.3062955534844055,
            "naucs_at_100_std": 0.19345305761479215,
            "naucs_at_100_diff1": -0.2440837194629938
        },
        "vidore/tabfquad_test_subsampled": {
            "ndcg_at_1": 0.76786,
            "ndcg_at_3": 0.82092,
            "ndcg_at_5": 0.82537,
            "ndcg_at_10": 0.836,
            "ndcg_at_20": 0.84227,
            "ndcg_at_50": 0.85136,
            "ndcg_at_100": 0.85623,
            "map_at_1": 0.76786,
            "map_at_3": 0.80833,
            "map_at_5": 0.81083,
            "map_at_10": 0.81535,
            "map_at_20": 0.81705,
            "map_at_50": 0.81846,
            "map_at_100": 0.81896,
            "recall_at_1": 0.76786,
            "recall_at_3": 0.85714,
            "recall_at_5": 0.86786,
            "recall_at_10": 0.9,
            "recall_at_20": 0.925,
            "recall_at_50": 0.97143,
            "recall_at_100": 1.0,
            "precision_at_1": 0.76786,
            "precision_at_3": 0.28571,
            "precision_at_5": 0.17357,
            "precision_at_10": 0.09,
            "precision_at_20": 0.04625,
            "precision_at_50": 0.01943,
            "precision_at_100": 0.01,
            "mrr_at_1": 0.7678571428571429,
            "mrr_at_3": 0.8071428571428573,
            "mrr_at_5": 0.81125,
            "mrr_at_10": 0.8151077097505668,
            "mrr_at_20": 0.8168129570408706,
            "mrr_at_50": 0.8182362693578513,
            "mrr_at_100": 0.8187353303445248,
            "naucs_at_1_max": 0.7177212679017732,
            "naucs_at_1_std": 0.44666957591145295,
            "naucs_at_1_diff1": 0.8633157456262146,
            "naucs_at_3_max": 0.6992711370262391,
            "naucs_at_3_std": 0.5656827016520902,
            "naucs_at_3_diff1": 0.7749271137026231,
            "naucs_at_5_max": 0.7027784293794164,
            "naucs_at_5_std": 0.5667631037089179,
            "naucs_at_5_diff1": 0.7667526780827264,
            "naucs_at_10_max": 0.7079998666133144,
            "naucs_at_10_std": 0.6723356009070299,
            "naucs_at_10_diff1": 0.7870981726023749,
            "naucs_at_20_max": 0.6686896981014611,
            "naucs_at_20_std": 0.6413676581743812,
            "naucs_at_20_diff1": 0.7568138366457667,
            "naucs_at_50_max": 0.7633636788048568,
            "naucs_at_50_std": 0.4874533146592006,
            "naucs_at_50_diff1": 0.6957282913165369,
            "naucs_at_100_max": 1.0,
            "naucs_at_100_std": 1.0,
            "naucs_at_100_diff1": 1.0
        },
        "vidore/syntheticDocQA_artificial_intelligence_test": {
            "ndcg_at_1": 0.87,
            "ndcg_at_3": 0.91024,
            "ndcg_at_5": 0.92703,
            "ndcg_at_10": 0.92703,
            "ndcg_at_20": 0.92703,
            "ndcg_at_50": 0.93125,
            "ndcg_at_100": 0.93125,
            "map_at_1": 0.87,
            "map_at_3": 0.9,
            "map_at_5": 0.9095,
            "map_at_10": 0.9095,
            "map_at_20": 0.9095,
            "map_at_50": 0.91029,
            "map_at_100": 0.91029,
            "recall_at_1": 0.87,
            "recall_at_3": 0.94,
            "recall_at_5": 0.98,
            "recall_at_10": 0.98,
            "recall_at_20": 0.98,
            "recall_at_50": 1.0,
            "recall_at_100": 1.0,
            "precision_at_1": 0.87,
            "precision_at_3": 0.31333,
            "precision_at_5": 0.196,
            "precision_at_10": 0.098,
            "precision_at_20": 0.049,
            "precision_at_50": 0.02,
            "precision_at_100": 0.01,
            "mrr_at_1": 0.87,
            "mrr_at_3": 0.905,
            "mrr_at_5": 0.9125,
            "mrr_at_10": 0.9125,
            "mrr_at_20": 0.9125,
            "mrr_at_50": 0.9132886904761907,
            "mrr_at_100": 0.9132886904761907,
            "naucs_at_1_max": 0.39580093312597203,
            "naucs_at_1_std": 0.016514848552173455,
            "naucs_at_1_diff1": 0.7961934384951498,
            "naucs_at_3_max": 0.6195922813569831,
            "naucs_at_3_std": 0.21148459383753418,
            "naucs_at_3_diff1": 0.8249299719887904,
            "naucs_at_5_max": 1.0,
            "naucs_at_5_std": 0.45611577964519334,
            "naucs_at_5_diff1": 1.0,
            "naucs_at_10_max": 1.0,
            "naucs_at_10_std": 0.45611577964519334,
            "naucs_at_10_diff1": 1.0,
            "naucs_at_20_max": 1.0,
            "naucs_at_20_std": 0.45611577964519334,
            "naucs_at_20_diff1": 1.0,
            "naucs_at_50_max": null,
            "naucs_at_50_std": null,
            "naucs_at_50_diff1": null,
            "naucs_at_100_max": null,
            "naucs_at_100_std": null,
            "naucs_at_100_diff1": null
        },
        "vidore/economics_reports_eng_v2": {
            "ndcg_at_1": 0.67241,
            "ndcg_at_3": 0.60459,
            "ndcg_at_5": 0.58473,
            "ndcg_at_10": 0.55836,
            "ndcg_at_20": 0.5607,
            "ndcg_at_50": 0.62374,
            "ndcg_at_100": 0.66912,
            "map_at_1": 0.06963,
            "map_at_3": 0.17752,
            "map_at_5": 0.23588,
            "map_at_10": 0.3044,
            "map_at_20": 0.34514,
            "map_at_50": 0.39603,
            "map_at_100": 0.42653,
            "recall_at_1": 0.06963,
            "recall_at_3": 0.23912,
            "recall_at_5": 0.32597,
            "recall_at_10": 0.44744,
            "recall_at_20": 0.55177,
            "recall_at_50": 0.74783,
            "recall_at_100": 0.87864,
            "precision_at_1": 0.67241,
            "precision_at_3": 0.55747,
            "precision_at_5": 0.51724,
            "precision_at_10": 0.41034,
            "precision_at_20": 0.28879,
            "precision_at_50": 0.18207,
            "precision_at_100": 0.12345,
            "mrr_at_1": 0.6551724137931034,
            "mrr_at_3": 0.7557471264367817,
            "mrr_at_5": 0.7600574712643678,
            "mrr_at_10": 0.7667624521072798,
            "mrr_at_20": 0.7677766508902413,
            "mrr_at_50": 0.7683924144370393,
            "mrr_at_100": 0.7683924144370393,
            "naucs_at_1_max": 0.24468152771990637,
            "naucs_at_1_std": 0.08687064845164325,
            "naucs_at_1_diff1": 0.011855734404369787,
            "naucs_at_3_max": 0.34577183109566345,
            "naucs_at_3_std": 0.24170318625391884,
            "naucs_at_3_diff1": -0.14082564121145513,
            "naucs_at_5_max": 0.37965027663336187,
            "naucs_at_5_std": 0.33743560759501545,
            "naucs_at_5_diff1": -0.2340308920635533,
            "naucs_at_10_max": 0.4680752680323528,
            "naucs_at_10_std": 0.3958829546397268,
            "naucs_at_10_diff1": -0.22878537154003714,
            "naucs_at_20_max": 0.4624952474091262,
            "naucs_at_20_std": 0.3684253981851255,
            "naucs_at_20_diff1": -0.22153415732811885,
            "naucs_at_50_max": 0.38562489552530244,
            "naucs_at_50_std": 0.3400818394033317,
            "naucs_at_50_diff1": -0.21568868174488262,
            "naucs_at_100_max": 0.3573382642954346,
            "naucs_at_100_std": 0.34272152757435836,
            "naucs_at_100_diff1": -0.20916881259451783
        },
        "vidore/vidore_v3_energy": {
            "ndcg_at_1": 0.37527,
            "ndcg_at_3": 0.42847,
            "ndcg_at_5": 0.45965,
            "ndcg_at_10": 0.49863,
            "ndcg_at_20": 0.52884,
            "ndcg_at_50": 0.56144,
            "ndcg_at_100": 0.57881,
            "map_at_1": 0.22039,
            "map_at_3": 0.32357,
            "map_at_5": 0.35781,
            "map_at_10": 0.38847,
            "map_at_20": 0.40509,
            "map_at_50": 0.4168,
            "map_at_100": 0.42114,
            "recall_at_1": 0.22039,
            "recall_at_3": 0.40984,
            "recall_at_5": 0.50413,
            "recall_at_10": 0.62864,
            "recall_at_20": 0.72524,
            "recall_at_50": 0.83642,
            "recall_at_100": 0.90874,
            "precision_at_1": 0.39448,
            "precision_at_3": 0.27417,
            "precision_at_5": 0.21807,
            "precision_at_10": 0.14859,
            "precision_at_20": 0.09464,
            "precision_at_50": 0.04973,
            "precision_at_100": 0.02911,
            "mrr_at_1": 0.39826839826839827,
            "mrr_at_3": 0.5045093795093804,
            "mrr_at_5": 0.5256403318903337,
            "mrr_at_10": 0.5415657424586006,
            "mrr_at_20": 0.5467293431004318,
            "mrr_at_50": 0.5484688417473473,
            "mrr_at_100": 0.5486923125173654,
            "naucs_at_1_max": 0.06624159527958148,
            "naucs_at_1_std": -0.13182982675567717,
            "naucs_at_1_diff1": 0.35209984436102526,
            "naucs_at_3_max": 0.057066188758709196,
            "naucs_at_3_std": -0.14014287845030562,
            "naucs_at_3_diff1": 0.1599032544172542,
            "naucs_at_5_max": 0.042631805044403406,
            "naucs_at_5_std": -0.15870971971990708,
            "naucs_at_5_diff1": 0.10583862929730796,
            "naucs_at_10_max": 0.022494906973351818,
            "naucs_at_10_std": -0.1516366809710436,
            "naucs_at_10_diff1": -0.00016560241486978966,
            "naucs_at_20_max": 0.013994855145259348,
            "naucs_at_20_std": -0.12407945435144623,
            "naucs_at_20_diff1": -0.049991548840776306,
            "naucs_at_50_max": 0.022348985833140007,
            "naucs_at_50_std": -0.07124408465434282,
            "naucs_at_50_diff1": -0.11160924259965294,
            "naucs_at_100_max": 0.023734360106538142,
            "naucs_at_100_std": -0.03606933051901125,
            "naucs_at_100_diff1": -0.1310450056106328
        },
        "vidore/economics_reports_v2": {
            "ndcg_at_1": 0.57328,
            "ndcg_at_3": 0.53471,
            "ndcg_at_5": 0.52184,
            "ndcg_at_10": 0.51306,
            "ndcg_at_20": 0.52785,
            "ndcg_at_50": 0.59409,
            "ndcg_at_100": 0.63625,
            "map_at_1": 0.05986,
            "map_at_3": 0.14718,
            "map_at_5": 0.19989,
            "map_at_10": 0.26535,
            "map_at_20": 0.31047,
            "map_at_50": 0.36204,
            "map_at_100": 0.38971,
            "recall_at_1": 0.05986,
            "recall_at_3": 0.20175,
            "recall_at_5": 0.29374,
            "recall_at_10": 0.41993,
            "recall_at_20": 0.53939,
            "recall_at_50": 0.74225,
            "recall_at_100": 0.86983,
            "precision_at_1": 0.57328,
            "precision_at_3": 0.49856,
            "precision_at_5": 0.46293,
            "precision_at_10": 0.38836,
            "precision_at_20": 0.2847,
            "precision_at_50": 0.18241,
            "precision_at_100": 0.12112,
            "mrr_at_1": 0.5689655172413793,
            "mrr_at_3": 0.6860632183908045,
            "mrr_at_5": 0.6996408045977011,
            "mrr_at_10": 0.7091646141215107,
            "mrr_at_20": 0.7096717135129914,
            "mrr_at_50": 0.7104238496202624,
            "mrr_at_100": 0.7104238496202624,
            "naucs_at_1_max": 0.3106820332585339,
            "naucs_at_1_std": 0.2609890856117384,
            "naucs_at_1_diff1": 0.07153376968175658,
            "naucs_at_3_max": 0.28217559321565566,
            "naucs_at_3_std": 0.22792138686222854,
            "naucs_at_3_diff1": 0.014253401634145456,
            "naucs_at_5_max": 0.2829930915979881,
            "naucs_at_5_std": 0.27062389338249804,
            "naucs_at_5_diff1": -0.03957305939485397,
            "naucs_at_10_max": 0.2628683940691712,
            "naucs_at_10_std": 0.26856694628186034,
            "naucs_at_10_diff1": -0.11712740675039437,
            "naucs_at_20_max": 0.22166041334952613,
            "naucs_at_20_std": 0.2800777305659196,
            "naucs_at_20_diff1": -0.12988892770983104,
            "naucs_at_50_max": 0.17837822040266466,
            "naucs_at_50_std": 0.2792069845994825,
            "naucs_at_50_diff1": -0.13360833735266028,
            "naucs_at_100_max": 0.1876547272816409,
            "naucs_at_100_std": 0.28859010160507786,
            "naucs_at_100_diff1": -0.13324038534018917
        },
        "vidore/esg_reports_eng_v2": {
            "ndcg_at_1": 0.49123,
            "ndcg_at_3": 0.4876,
            "ndcg_at_5": 0.50767,
            "ndcg_at_10": 0.55556,
            "ndcg_at_20": 0.57699,
            "ndcg_at_50": 0.60951,
            "ndcg_at_100": 0.62306,
            "map_at_1": 0.22354,
            "map_at_3": 0.35507,
            "map_at_5": 0.38501,
            "map_at_10": 0.43497,
            "map_at_20": 0.44924,
            "map_at_50": 0.46141,
            "map_at_100": 0.46548,
            "recall_at_1": 0.22354,
            "recall_at_3": 0.44985,
            "recall_at_5": 0.52519,
            "recall_at_10": 0.6821,
            "recall_at_20": 0.75675,
            "recall_at_50": 0.87022,
            "recall_at_100": 0.91322,
            "precision_at_1": 0.49123,
            "precision_at_3": 0.33333,
            "precision_at_5": 0.26316,
            "precision_at_10": 0.18421,
            "precision_at_20": 0.10877,
            "precision_at_50": 0.05474,
            "precision_at_100": 0.0314,
            "mrr_at_1": 0.43859649122807015,
            "mrr_at_3": 0.567251461988304,
            "mrr_at_5": 0.585672514619883,
            "mrr_at_10": 0.5922514619883041,
            "mrr_at_20": 0.5950629779577148,
            "mrr_at_50": 0.5970309069851404,
            "mrr_at_100": 0.5970309069851404,
            "naucs_at_1_max": 0.21148088278843497,
            "naucs_at_1_std": 0.27364361478859595,
            "naucs_at_1_diff1": 0.17193693008106317,
            "naucs_at_3_max": 0.0332146064567773,
            "naucs_at_3_std": 0.19928772757895383,
            "naucs_at_3_diff1": -0.07448131256087642,
            "naucs_at_5_max": 0.023808183802180933,
            "naucs_at_5_std": 0.05536873793501547,
            "naucs_at_5_diff1": -0.014255162957568276,
            "naucs_at_10_max": 0.060034161321225694,
            "naucs_at_10_std": 0.11165929392171386,
            "naucs_at_10_diff1": 0.028973180470065973,
            "naucs_at_20_max": 0.024178360811740515,
            "naucs_at_20_std": 0.12068467810263647,
            "naucs_at_20_diff1": 0.07303388767511548,
            "naucs_at_50_max": -0.0001985883106536588,
            "naucs_at_50_std": 0.118913500036214,
            "naucs_at_50_diff1": 0.10234909934999371,
            "naucs_at_100_max": -0.05270819380200488,
            "naucs_at_100_std": 0.15635880384023354,
            "naucs_at_100_diff1": 0.08394520513121842
        },
        "vidore/arxivqa_test_subsampled": {
            "ndcg_at_1": 0.724,
            "ndcg_at_3": 0.79195,
            "ndcg_at_5": 0.80744,
            "ndcg_at_10": 0.82255,
            "ndcg_at_20": 0.83074,
            "ndcg_at_50": 0.83632,
            "ndcg_at_100": 0.83729,
            "map_at_1": 0.724,
            "map_at_3": 0.77533,
            "map_at_5": 0.78383,
            "map_at_10": 0.79021,
            "map_at_20": 0.7925,
            "map_at_50": 0.79341,
            "map_at_100": 0.79349,
            "recall_at_1": 0.724,
            "recall_at_3": 0.84,
            "recall_at_5": 0.878,
            "recall_at_10": 0.924,
            "recall_at_20": 0.956,
            "recall_at_50": 0.984,
            "recall_at_100": 0.99,
            "precision_at_1": 0.724,
            "precision_at_3": 0.28,
            "precision_at_5": 0.1756,
            "precision_at_10": 0.0924,
            "precision_at_20": 0.0478,
            "precision_at_50": 0.01968,
            "precision_at_100": 0.0099,
            "mrr_at_1": 0.724,
            "mrr_at_3": 0.7760000000000001,
            "mrr_at_5": 0.7847999999999998,
            "mrr_at_10": 0.7901404761904761,
            "mrr_at_20": 0.7927945699295543,
            "mrr_at_50": 0.7937108189970857,
            "mrr_at_100": 0.7937925534181726,
            "naucs_at_1_max": 0.5501764574146866,
            "naucs_at_1_std": -0.4550940977504569,
            "naucs_at_1_diff1": 0.9155977543187663,
            "naucs_at_3_max": 0.5822471772214037,
            "naucs_at_3_std": -0.3716126656848293,
            "naucs_at_3_diff1": 0.8399300441826215,
            "naucs_at_5_max": 0.5779498675361717,
            "naucs_at_5_std": -0.36034863852267784,
            "naucs_at_5_diff1": 0.815804737345392,
            "naucs_at_10_max": 0.6078799941029033,
            "naucs_at_10_std": -0.20827804806133232,
            "naucs_at_10_diff1": 0.7929259423067462,
            "naucs_at_20_max": 0.5578686019862503,
            "naucs_at_20_std": -0.09222476869535538,
            "naucs_at_20_diff1": 0.8119854002206963,
            "naucs_at_50_max": 0.39262371615313707,
            "naucs_at_50_std": -0.27252567693743607,
            "naucs_at_50_diff1": 0.7557773109243678,
            "naucs_at_100_max": 0.9444444444444274,
            "naucs_at_100_std": 0.4902894491129706,
            "naucs_at_100_diff1": 0.7637721755368587
        },
        "vidore/shiftproject_test": {
            "ndcg_at_1": 0.58,
            "ndcg_at_3": 0.70333,
            "ndcg_at_5": 0.73691,
            "ndcg_at_10": 0.74985,
            "ndcg_at_20": 0.75979,
            "ndcg_at_50": 0.76179,
            "ndcg_at_100": 0.76679,
            "map_at_1": 0.58,
            "map_at_3": 0.67333,
            "map_at_5": 0.69233,
            "map_at_10": 0.69768,
            "map_at_20": 0.70032,
            "map_at_50": 0.70065,
            "map_at_100": 0.70112,
            "recall_at_1": 0.58,
            "recall_at_3": 0.79,
            "recall_at_5": 0.87,
            "recall_at_10": 0.91,
            "recall_at_20": 0.95,
            "recall_at_50": 0.96,
            "recall_at_100": 0.99,
            "precision_at_1": 0.58,
            "precision_at_3": 0.26333,
            "precision_at_5": 0.174,
            "precision_at_10": 0.091,
            "precision_at_20": 0.0475,
            "precision_at_50": 0.0192,
            "precision_at_100": 0.0099,
            "mrr_at_1": 0.58,
            "mrr_at_3": 0.6733333333333333,
            "mrr_at_5": 0.6938333333333334,
            "mrr_at_10": 0.6976230158730159,
            "mrr_at_20": 0.7003035714285716,
            "mrr_at_50": 0.7006369047619049,
            "mrr_at_100": 0.7011212053208574,
            "naucs_at_1_max": 0.14687871840264646,
            "naucs_at_1_std": -0.323693298894274,
            "naucs_at_1_diff1": 0.7200133499724298,
            "naucs_at_3_max": 0.2774665159785509,
            "naucs_at_3_std": -0.11005843172145156,
            "naucs_at_3_diff1": 0.4006059585928292,
            "naucs_at_5_max": 0.4687847145078876,
            "naucs_at_5_std": -0.10842035103310264,
            "naucs_at_5_diff1": 0.2374657483522184,
            "naucs_at_10_max": 0.39194937234152777,
            "naucs_at_10_std": -0.18684510841373445,
            "naucs_at_10_diff1": 0.4088079676314959,
            "naucs_at_20_max": 0.16591970121382563,
            "naucs_at_20_std": -0.4749766573295887,
            "naucs_at_20_diff1": 0.3409897292250282,
            "naucs_at_50_max": 0.06886087768441068,
            "naucs_at_50_std": -0.30578898225956497,
            "naucs_at_50_diff1": 0.2089169000933705,
            "naucs_at_100_max": 0.35807656395892007,
            "naucs_at_100_std": 0.7222222222222041,
            "naucs_at_100_diff1": 0.12278244631185525
        },
        "vidore/esg_reports_v2": {
            "ndcg_at_1": 0.44298,
            "ndcg_at_3": 0.47193,
            "ndcg_at_5": 0.49837,
            "ndcg_at_10": 0.5474,
            "ndcg_at_20": 0.5716,
            "ndcg_at_50": 0.5975,
            "ndcg_at_100": 0.61284,
            "map_at_1": 0.20314,
            "map_at_3": 0.34077,
            "map_at_5": 0.37588,
            "map_at_10": 0.42501,
            "map_at_20": 0.44207,
            "map_at_50": 0.45285,
            "map_at_100": 0.45705,
            "recall_at_1": 0.20314,
            "recall_at_3": 0.43743,
            "recall_at_5": 0.52664,
            "recall_at_10": 0.69191,
            "recall_at_20": 0.76928,
            "recall_at_50": 0.85621,
            "recall_at_100": 0.9098,
            "precision_at_1": 0.44298,
            "precision_at_3": 0.33333,
            "precision_at_5": 0.26754,
            "precision_at_10": 0.18421,
            "precision_at_20": 0.11206,
            "precision_at_50": 0.05491,
            "precision_at_100": 0.03154,
            "mrr_at_1": 0.42543859649122806,
            "mrr_at_3": 0.5526315789473683,
            "mrr_at_5": 0.5736842105263158,
            "mrr_at_10": 0.5857995683653578,
            "mrr_at_20": 0.5874272352890773,
            "mrr_at_50": 0.588760087837605,
            "mrr_at_100": 0.5888357079222994,
            "naucs_at_1_max": 0.24195677764338813,
            "naucs_at_1_std": 0.27901845789921087,
            "naucs_at_1_diff1": 0.3276377929633201,
            "naucs_at_3_max": 0.11749976712347417,
            "naucs_at_3_std": 0.11649723301386912,
            "naucs_at_3_diff1": 0.06250508070169579,
            "naucs_at_5_max": 0.11408629424473195,
            "naucs_at_5_std": 0.08015860959084256,
            "naucs_at_5_diff1": 0.08746238934894053,
            "naucs_at_10_max": 0.14805693093740213,
            "naucs_at_10_std": 0.07124614321319477,
            "naucs_at_10_diff1": 0.12955038174257508,
            "naucs_at_20_max": 0.14564954633798843,
            "naucs_at_20_std": 0.11210905166068041,
            "naucs_at_20_diff1": 0.08153822646743188,
            "naucs_at_50_max": 0.07012897589447661,
            "naucs_at_50_std": 0.06304881874931847,
            "naucs_at_50_diff1": 0.06178209431697991,
            "naucs_at_100_max": 0.04923316699253806,
            "naucs_at_100_std": 0.09636916806782066,
            "naucs_at_100_diff1": 0.051283819800501104
        }
    }
}